m3c2/__init__.py
m3c2/chain.py
m3c2/proposal.py
m3c2/sampler.py
m3c2/gb/__init__.py
m3c2/gb/fstatistics.py
m3c2/gb/likelihood.py
m3c2/gb/proposal.py
m3c2-1.0.dist-info/LICENSE
m3c2-1.0.dist-info/METADATA
m3c2-1.0.dist-info/WHEEL
m3c2-1.0.dist-info/top_level.txt
m3c2-1.0.dist-info/RECORD
