Metadata-Version: 2.1
Name: m3c2
Version: 1.0
Summary: MultiChain MCMC sampler which uses several build-in proposals
Author: S. Babak
License: GNU AFFERO GENERAL PUBLIC LICENSE
Project-URL: documentation, https://lisa-apc.pages.in2p3.fr/m3c2
Requires-Python: >=3.7
License-File: LICENSE
Requires-Dist: numpy
Requires-Dist: scikit-learn
Requires-Dist: acor
